azure/mgmt/resourcehealth/__init__.py
azure/mgmt/resourcehealth/_configuration.py
azure/mgmt/resourcehealth/_patch.py
azure/mgmt/resourcehealth/_resource_health_mgmt_client.py
azure/mgmt/resourcehealth/_serialization.py
azure/mgmt/resourcehealth/_version.py
azure/mgmt/resourcehealth/py.typed
azure/mgmt/resourcehealth/aio/__init__.py
azure/mgmt/resourcehealth/aio/_configuration.py
azure/mgmt/resourcehealth/aio/_patch.py
azure/mgmt/resourcehealth/aio/_resource_health_mgmt_client.py
azure/mgmt/resourcehealth/aio/operations/__init__.py
azure/mgmt/resourcehealth/aio/operations/_availability_statuses_operations.py
azure/mgmt/resourcehealth/aio/operations/_child_availability_statuses_operations.py
azure/mgmt/resourcehealth/aio/operations/_child_resources_operations.py
azure/mgmt/resourcehealth/aio/operations/_emerging_issues_operations.py
azure/mgmt/resourcehealth/aio/operations/_event_operations.py
azure/mgmt/resourcehealth/aio/operations/_events_operations.py
azure/mgmt/resourcehealth/aio/operations/_impacted_resources_operations.py
azure/mgmt/resourcehealth/aio/operations/_metadata_operations.py
azure/mgmt/resourcehealth/aio/operations/_operations.py
azure/mgmt/resourcehealth/aio/operations/_patch.py
azure/mgmt/resourcehealth/aio/operations/_security_advisory_impacted_resources_operations.py
azure/mgmt/resourcehealth/models/__init__.py
azure/mgmt/resourcehealth/models/_models_py3.py
azure/mgmt/resourcehealth/models/_patch.py
azure/mgmt/resourcehealth/models/_resource_health_mgmt_client_enums.py
azure/mgmt/resourcehealth/operations/__init__.py
azure/mgmt/resourcehealth/operations/_availability_statuses_operations.py
azure/mgmt/resourcehealth/operations/_child_availability_statuses_operations.py
azure/mgmt/resourcehealth/operations/_child_resources_operations.py
azure/mgmt/resourcehealth/operations/_emerging_issues_operations.py
azure/mgmt/resourcehealth/operations/_event_operations.py
azure/mgmt/resourcehealth/operations/_events_operations.py
azure_mgmt_resourcehealth-1.0.0b6.dist-info/LICENSE
azure_mgmt_resourcehealth-1.0.0b6.dist-info/METADATA
azure_mgmt_resourcehealth-1.0.0b6.dist-info/WHEEL
azure_mgmt_resourcehealth-1.0.0b6.dist-info/top_level.txt
azure_mgmt_resourcehealth-1.0.0b6.dist-info/RECORD
